ktree/__init__.py
ktree-0.0.1.data/data/LICENSE
ktree-0.0.1.data/data/README.md
ktree-0.0.1.data/data/docs/requirements.txt
ktree-0.0.1.data/data/examples/ntree.py
ktree-0.0.1.data/data/examples/octree.py
ktree-0.0.1.data/data/examples/quadtree.py
ktree-0.0.1.data/data/examples/utree.py
ktree-0.0.1.data/scripts/ntree.py
ktree-0.0.1.data/scripts/octree.py
ktree-0.0.1.data/scripts/quadtree.py
ktree-0.0.1.data/scripts/utree.py
ktree-0.0.1.dist-info/LICENSE
ktree-0.0.1.dist-info/METADATA
ktree-0.0.1.dist-info/WHEEL
ktree-0.0.1.dist-info/top_level.txt
ktree-0.0.1.dist-info/RECORD
