Metadata-Version: 2.1
Name: ktree
Version: 0.0.1
Summary: This module provides a hierarchical spatial ordering structure, which can be used as a QuadTree or an Octree.
Home-page: https://github.com/SealtielFreak/ktree
Author: SealtielFreak
Author-email: sealtielfreak@yandex.com
License: WTFPL
Platform: UNKNOWN
Requires-Python: >=3.8
